magic_eight/__init__.py
magic_eight/answers.py
magic_eight/magic_eight.py
magic_eight/questions.py
magic_eight/shakes.py
magic_eight_ball-0.2.0.dist-info/LICENSE
magic_eight_ball-0.2.0.dist-info/METADATA
magic_eight_ball-0.2.0.dist-info/WHEEL
magic_eight_ball-0.2.0.dist-info/top_level.txt
magic_eight_ball-0.2.0.dist-info/RECORD
