Metadata-Version: 2.1
Name: magic-eight-ball
Version: 0.2.0
Summary: A fun and lighthearted Python package that emulates the classic Magic 8 Ball toy. This package allows users to ask questions and get random, playful responses. Built with rigorous software engineering practices, it serves as a joyful addition to any developer's toolbox.
Author-email: Alexandra Mastrangelo <arm9129@nyu.edu>, Natalie Trump <nht251@nyu.edu>
License: GNU GENERAL PUBLIC LICENSE
Project-URL: Homepage, https://github.com/software-students-fall2024/3-python-package-magic-eight
Keywords: python,package,fun
Requires-Python: >=3.11
License-File: LICENSE
